protopy/application.py
protopy/cli/__init__.py
protopy/cli/commands/__init__.py
protopy/cli/commands/generate_command.py
protopy/cli/commands/man_command.py
protopy/cli/commands/new_command.py
protopy/cli/resources/templates/new_template.zip
protopy/cli/sources/__init__.py
protopy/cli/sources/file_system_source.py
protopy/cli/sources/git_source.py
protopy/cli/sources/url_source.py
protopy/cli/sources/zip_source.py
protopy/cli/utils/__init__.py
protopy/cli/utils/resources.py
protopy/protopy.py
protopy_cli-0.2.0.dist-info/entry_points.txt
protopy_cli-0.2.0.dist-info/LICENSE
protopy_cli-0.2.0.dist-info/WHEEL
protopy_cli-0.2.0.dist-info/METADATA
protopy_cli-0.2.0.dist-info/RECORD
