Metadata-Version: 2.1
Name: protopy-cli
Version: 0.2.0
Summary: 
Author: bennylut
Requires-Python: >=3.6,<4.0
Classifier: Programming Language :: Python :: 3
Classifier: Programming Language :: Python :: 3.6
Classifier: Programming Language :: Python :: 3.7
Classifier: Programming Language :: Python :: 3.8
Classifier: Programming Language :: Python :: 3.9
Classifier: Programming Language :: Python :: 3.10
Requires-Dist: dataclasses (>=0.8); python_version >= "3.6" and python_version < "3.7"
Requires-Dist: importlib-resources (>=5,<6); python_version < "3.8"
Requires-Dist: protopy_lib (>=0.2.0,<0.3.0)
Requires-Dist: pygit2 (>=1.6.1,<2.0.0)
Requires-Dist: requests (>=2.26.0,<3.0.0)
Requires-Dist: tomlkit (>=0.7.2,<0.8.0)
Requires-Dist: typing-extensions (>=3.10.0.2,<4.0.0.0); python_version < "3.8"
